soldcli/__init__.py
soldcli/__main__.py
soldcli/cli.py
soldcli/commands/__init__.py
soldcli/commands/hello.py
soldcli/commands/info.py
soldcli/commands/pack1.py
soldcli/commands/pack2.py
soldcli/commands/run.py
soldcli/commands/run1.py
soldcli/commands/run2.py
soldcli/commands/run3.py
soldcli/commands/toml.py
soldcli/contents/__init__.py
soldcli/contents/diagnostic.py
soldcli/contents/hint.py
soldcli/contents/uv_templates.py
soldcli/tools/__init__.py
soldcli/tools/command_builder.py
soldcli/tools/file_operations.py
soldcli/tools/system_checker.py
soldcli/tools/system_diagnostics.py
soldcli-0.3.2.dist-info/METADATA
soldcli-0.3.2.dist-info/WHEEL
soldcli-0.3.2.dist-info/entry_points.txt
soldcli-0.3.2.dist-info/top_level.txt
soldcli-0.3.2.dist-info/RECORD
