Metadata-Version: 2.4
Name: soldcli
Version: 0.3.2
Summary: Convenient command line tool, providing magic tag function
Author-email: nphard001 <nphard001@gmail.com>
License: MIT
Project-URL: Homepage, https://github.com/nphard001
Keywords: api,python,utility
Classifier: Development Status :: 3 - Alpha
Classifier: Intended Audience :: Developers
Classifier: License :: OSI Approved :: MIT License
Classifier: Programming Language :: Python :: 3
Classifier: Programming Language :: Python :: 3.10
Classifier: Programming Language :: Python :: 3.11
Classifier: Programming Language :: Python :: 3.12
Classifier: Topic :: Software Development :: Libraries :: Python Modules
Classifier: Topic :: Utilities
Requires-Python: >=3.10
Requires-Dist: click>=8.0.0
Provides-Extra: dev
Requires-Dist: pytest>=7.0.0; extra == "dev"
